asita/application.py
asita/handlers/http_request_handler.py
asita/handlers/request.py
asita/handlers/response.py
asita/utils/http_types.py
asita/utils/route.py
asita-0.2.0.dist-info/METADATA
asita-0.2.0.dist-info/WHEEL
asita-0.2.0.dist-info/top_level.txt
asita-0.2.0.dist-info/RECORD
