Metadata-Version: 2.1
Name: asita
Version: 0.2.0
Summary: A web application framework
Home-page: https://github.com/Matteo0810/PyServ
Author: Mattéo Gaillard
License: UNKNOWN
Platform: UNKNOWN
Classifier: Programming Language :: Python :: 3
Classifier: License :: OSI Approved :: MIT License
Classifier: Operating System :: OS Independent
Requires-Python: >=3.9
